amisrsynthdata/__init__.py
amisrsynthdata/beamcodes.h5
amisrsynthdata/ionosphere.py
amisrsynthdata/radar.py
amisrsynthdata/syntheticdata.py
amisrsynthdata/state_functions/__init__.py
amisrsynthdata/state_functions/density.py
amisrsynthdata/state_functions/gemini_utils.py
amisrsynthdata/state_functions/temperature.py
amisrsynthdata/state_functions/utils.py
amisrsynthdata/state_functions/velocity.py
amisrsynthdata-1.1.8.dist-info/LICENSE
amisrsynthdata-1.1.8.dist-info/METADATA
amisrsynthdata-1.1.8.dist-info/WHEEL
amisrsynthdata-1.1.8.dist-info/entry_points.txt
amisrsynthdata-1.1.8.dist-info/top_level.txt
amisrsynthdata-1.1.8.dist-info/RECORD
