Metadata-Version: 2.1
Name: amisrsynthdata
Version: 1.1.8
Summary: Tool for generating synthetic AMISR data files.
Author-email: "L. Lamarche" <leslie.lamarche@sri.com>
License: GNU GENERAL PUBLIC LICENSE
Project-URL: Homepage, https://github.com/amisr/amisrsynthdata
Project-URL: Bug Tracker, https://github.com/amisr/amisrsynthdata/issues
Keywords: AMISR,synthetic,data
Classifier: Programming Language :: Python :: 3
Classifier: Topic :: Scientific/Engineering
Classifier: Intended Audience :: Science/Research
Classifier: License :: OSI Approved :: GNU General Public License (GPL)
Classifier: Natural Language :: English
Classifier: Programming Language :: Python
Classifier: Operating System :: OS Independent
Requires-Python: <3.12,>=3.7
License-File: LICENSE
Requires-Dist: numpy
Requires-Dist: h5py
Requires-Dist: apexpy
Requires-Dist: pymap3d
Requires-Dist: pyyaml
Requires-Dist: importlib-resources ; python_version < "3.9"
Provides-Extra: plots
Requires-Dist: matplotlib ; extra == 'plots'
Requires-Dist: cartopy ; extra == 'plots'
